linear_cae/__init__.py
linear_cae/baselines.py
linear_cae/components/__init__.py
linear_cae/components/blocks.py
linear_cae/components/diffusion.py
linear_cae/components/ema.py
linear_cae/components/frontends.py
linear_cae/components/generator.py
linear_cae/inference.py
linear_cae/utils.py
linear_cae-0.1.4.dist-info/METADATA
linear_cae-0.1.4.dist-info/WHEEL
linear_cae-0.1.4.dist-info/entry_points.txt
linear_cae-0.1.4.dist-info/licenses/LICENSE
linear_cae-0.1.4.dist-info/RECORD
