Metadata-Version: 2.4
Name: linear-cae
Version: 0.1.4
Summary: Linear Consistency Autoencoders
License-File: LICENSE
Author: Bernardo Torres
Requires-Python: >=3.11
Classifier: Programming Language :: Python :: 3
Classifier: Programming Language :: Python :: 3.11
Classifier: Programming Language :: Python :: 3.12
Classifier: Programming Language :: Python :: 3.13
Classifier: Programming Language :: Python :: 3.14
Requires-Dist: PyYAML
Requires-Dist: huggingface_hub
Requires-Dist: matplotlib (>=3.10.1)
Requires-Dist: numpy (>=1.23.5,<2.0.0)
Requires-Dist: soundfile (>=0.13.1)
Requires-Dist: torch (>=2.0.1)
